Lab/misc-assignments/assignment-3/memory_sim/data_ram.v
module data_ram #(
    parameter integer ADDR = 32,
    parameter integer DATA = 32
) (
    clka,
    ena,
    addra,
    wea,
    dina,
    douta
);
  input clka, ena, wea;
  input [ADDR-1:0] addra;
  input [DATA-1:0] dina;
  output reg [DATA-1:0] douta;

  localparam integer SIZE = 1 << ADDR;
  reg [DATA-1:0] mem[SIZE];

  initial begin
    $readmemh("data_ram.mem", mem);
  end

  always @(posedge clka) begin
    if (ena) begin
      if (wea) begin
        mem[addra] <= dina;
      end
      douta <= mem[addra];
    end
  end

endmodule

Lab/misc-assignments/assignment-3/memory_sim/address_rom.v
module address_rom #(
  parameter integer ADDR = 32,
  parameter integer DATA = 32
) (
    clka,
    ena,
    addra,
    douta
);
  input clka, ena;
  input [ADDR-1:0] addra;
  output reg [DATA-1:0] douta;

  localparam integer SIZE = 1 << ADDR;
  reg [DATA-1:0] mem[SIZE];

  initial begin
    $readmemh("program.mem", mem);
  end

  always @(posedge clka) begin
    if(ena) begin
      douta <= mem[addra];
    end
  end

endmodule

Lab/misc-assignments/assignment-3/bram_ram_rom_practice.v
module bram_ram_rom_practice (
    clk,
    reset,
    start,
    done,
    result_out
);
  input clk, reset, start;
  output reg done;
  output reg [31:0] result_out;

  reg rom_en;
  reg [2:0] rom_addr;
  wire [3:0] rom_data;

  address_rom #(
      .ADDR(3),
      .DATA(4)
  ) rom_inst (
      .clka (clk),
      .ena  (rom_en),
      .addra(rom_addr),
      .douta(rom_data)
  );

  reg ram_en, ram_we;
  reg  [ 3:0] ram_addr;
  reg  [31:0] ram_write_data;
  wire [31:0] ram_read_data;

  data_ram #(
      .ADDR(4),
      .DATA(32)
  ) ram_inst (
      .clka (clk),
      .ena  (ram_en),
      .wea  (ram_we),
      .addra(ram_addr),
      .dina (ram_write_data),
      .douta(ram_read_data)
  );

  localparam [2:0]
    IDLE       = 3'b000,
    ROMREQUEST = 3'b001,
    RAMREQUEST = 3'b010,
    WAIT       = 3'b011,
    ACCUMULATE = 3'b100,
    RAMWRITE   = 3'b101,
    RAMREAD    = 3'b110,
    SETRESULT  = 3'b111;

  reg [2:0] current_state, next_state;
  reg [ 3:0] count;
  reg [31:0] acc;

  always @(posedge clk or posedge reset) begin
    if (reset) current_state <= IDLE;
    else current_state <= next_state;
  end

  always @(*) begin
    next_state = current_state;
    case (current_state)
      IDLE:       next_state = start ? ROMREQUEST : IDLE;
      ROMREQUEST: next_state = RAMREQUEST;
      RAMREQUEST: next_state = WAIT;
      WAIT:       next_state = ACCUMULATE;
      ACCUMULATE: next_state = (count == 4'd7) ? RAMWRITE : ROMREQUEST;
      RAMWRITE:   next_state = RAMREAD;
      RAMREAD:    next_state = SETRESULT;
      SETRESULT:  next_state = SETRESULT;
      default:    next_state = IDLE;
    endcase
  end

  always @(posedge clk or posedge reset) begin
    if (reset) begin
      count      <= 4'b0;
      acc        <= 32'b0;
      done       <= 1'b0;
      result_out <= 32'b0;
    end else begin
      case (current_state)
        ACCUMULATE: begin
          acc   <= acc + ram_read_data;
          count <= count + 1'b1;
        end
        SETRESULT: begin
          result_out <= ram_read_data;
          done       <= 1'b1;
        end
        default: ;
      endcase
    end
  end

  always @(*) begin
    rom_en         = 1'b0;
    rom_addr       = 3'b0;
    ram_en         = 1'b0;
    ram_we         = 1'b0;
    ram_addr       = 4'b0;
    ram_write_data = 32'b0;

    case (current_state)
      ROMREQUEST: begin
        rom_en   = 1'b1;
        rom_addr = count[2:0];
      end
      RAMREQUEST: begin
        ram_en   = 1'b1;
        ram_addr = rom_data;
        ram_we   = 1'b0;
      end
      RAMWRITE: begin
        ram_en         = 1'b1;
        ram_addr       = 4'b1111;
        ram_write_data = acc;
        ram_we         = 1'b1;
      end
      RAMREAD: begin
        ram_en   = 1'b1;
        ram_addr = 4'b1111;
        ram_we   = 1'b0;
      end
      default: ;
    endcase
  end

endmodule

Lab/misc-assignments/assignment-3/bram_ram_rom_practice_tb.v
`timescale 1ns / 1ps

module bram_ram_rom_practice_tb;

  reg clk;
  reg reset;
  reg start;
  wire done;
  wire [31:0] result_out;

  // ---- DUT instantiation ----
  bram_ram_rom_practice dut (
      .clk       (clk),
      .reset     (reset),
      .start     (start),
      .done      (done),
      .result_out(result_out)
  );

  // ---- Clock generation: 10ns period (100MHz) ----
  initial clk = 1'b0;
  always #5 clk = ~clk;

  // ---- Waveform dump ----
  initial begin
    $dumpfile("bram_ram_rom_practice_tb.vcd");
    $dumpvars(0, bram_ram_rom_practice_tb);
  end

  // ---- Stimulus ----
  initial begin
    // 1. Apply reset
    reset = 1'b1;
    start = 1'b0;
    @(posedge clk);
    @(posedge clk);

    // 2. Release reset
    reset = 1'b0;
    @(posedge clk);

    // 3. Pulse start for one clock edge
    start = 1'b1;
    @(posedge clk);
    start = 1'b0;

    // 4. Wait until done = 1 (with a safety timeout so a bug doesn't hang forever)
    fork
      begin
        wait (done == 1'b1);
      end
      begin
        #10000;
        $display("FAIL: timeout waiting for done (possible FSM lockup)");
        $finish;
      end
    join_any
    disable fork;

    // 5. Check result
    if (result_out == 32'h00000168) $display("PASS: result_out = %h, done = %b", result_out, done);
    else $display("FAIL: result = %h (expected 00000168)", result_out);

    // 6. Terminate
    $finish;
  end

endmodule

Lab/misc-assignments/assignment-3/bram_ram_rom_practice_tb.vcd
$date
	Sun Sep 27 21:38:03 2026
$end
$version
	Icarus Verilog
$end
$timescale
	1ps
$end
$scope module bram_ram_rom_practice_tb $end
$var wire 32 ! result_out [31:0] $end
$var wire 1 " done $end
$var reg 1 # clk $end
$var reg 1 $ reset $end
$var reg 1 % start $end
$scope module dut $end
$var wire 1 # clk $end
$var wire 1 $ reset $end
$var wire 1 % start $end
$var wire 4 & rom_data [3:0] $end
$var wire 32 ' ram_read_data [31:0] $end
$var parameter 3 ( ACCUMULATE $end
$var parameter 3 ) IDLE $end
$var parameter 3 * RAMREAD $end
$var parameter 3 + RAMREQUEST $end
$var parameter 3 , RAMWRITE $end
$var parameter 3 - ROMREQUEST $end
$var parameter 3 . SETRESULT $end
$var parameter 3 / WAIT $end
$var reg 32 0 acc [31:0] $end
$var reg 4 1 count [3:0] $end
$var reg 3 2 current_state [2:0] $end
$var reg 1 " done $end
$var reg 3 3 next_state [2:0] $end
$var reg 4 4 ram_addr [3:0] $end
$var reg 1 5 ram_en $end
$var reg 1 6 ram_we $end
$var reg 32 7 ram_write_data [31:0] $end
$var reg 32 8 result_out [31:0] $end
$var reg 3 9 rom_addr [2:0] $end
$var reg 1 : rom_en $end
$scope module ram_inst $end
$var wire 4 ; addra [3:0] $end
$var wire 1 # clka $end
$var wire 32 < dina [31:0] $end
$var wire 1 5 ena $end
$var wire 1 6 wea $end
$var parameter 32 = ADDR $end
$var parameter 32 > DATA $end
$var parameter 32 ? SIZE $end
$var reg 32 @ douta [31:0] $end
$upscope $end
$scope module rom_inst $end
$var wire 3 A addra [2:0] $end
$var wire 1 # clka $end
$var wire 1 : ena $end
$var parameter 32 B ADDR $end
$var parameter 32 C DATA $end
$var parameter 32 D SIZE $end
$var reg 4 E douta [3:0] $end
$upscope $end
$upscope $end
$upscope $end
$enddefinitions $end
$comment Show the parameter values. $end
$dumpall
b1000 D
b100 C
b11 B
b10000 ?
b100000 >
b100 =
b11 /
b111 .
b1 -
b101 ,
b10 +
b110 *
b0 )
b100 (
$end
#0
$dumpvars
bx E
b0 A
bx @
b0 <
b0 ;
0:
b0 9
b0 8
b0 7
06
05
b0 4
b0 3
b0 2
b0 1
b0 0
bx '
bx &
0%
1$
0#
0"
b0 !
$end
#5000
1#
#10000
0#
#15000
0$
1#
#20000
0#
#25000
b1 3
1%
1#
#30000
0#
#35000
1:
b1 2
b10 3
0%
1#
#40000
0#
#45000
b10 4
b10 ;
15
0:
b11 3
b10 &
b10 E
b10 2
1#
#50000
0#
#55000
b0 4
b0 ;
05
b100 3
b11110 '
b11110 @
b11 2
1#
#60000
0#
#65000
b1 3
b100 2
1#
#70000
0#
#75000
b10 3
b1 9
b1 A
1:
b1 2
b1 1
b11110 0
1#
#80000
0#
#85000
b101 4
b101 ;
15
b0 9
b0 A
0:
b11 3
b101 &
b101 E
b10 2
1#
#90000
0#
#95000
b0 4
b0 ;
05
b100 3
b111100 '
b111100 @
b11 2
1#
#100000
0#
#105000
b1 3
b100 2
1#
#110000
0#
#115000
b10 3
b10 9
b10 A
1:
b1 2
b10 1
b1011010 0
1#
#120000
0#
#125000
b1 4
b1 ;
15
b0 9
b0 A
0:
b11 3
b1 &
b1 E
b10 2
1#
#130000
0#
#135000
b0 4
b0 ;
05
b100 3
b10100 '
b10100 @
b11 2
1#
#140000
0#
#145000
b1 3
b100 2
1#
#150000
0#
#155000
b10 3
b11 9
b11 A
1:
b1 2
b11 1
b1101110 0
1#
#160000
0#
#165000
b111 4
b111 ;
15
b0 9
b0 A
0:
b11 3
b111 &
b111 E
b10 2
1#
#170000
0#
#175000
b0 4
b0 ;
05
b100 3
b1010000 '
b1010000 @
b11 2
1#
#180000
0#
#185000
b1 3
b100 2
1#
#190000
0#
#195000
b10 3
b100 9
b100 A
1:
b1 2
b100 1
b10111110 0
1#
#200000
0#
#205000
b11 4
b11 ;
15
b0 9
b0 A
0:
b11 3
b11 &
b11 E
b10 2
1#
#210000
0#
#215000
b0 4
b0 ;
05
b100 3
b101000 '
b101000 @
b11 2
1#
#220000
0#
#225000
b1 3
b100 2
1#
#230000
0#
#235000
b10 3
b101 9
b101 A
1:
b1 2
b101 1
b11100110 0
1#
#240000
0#
#245000
15
b0 9
b0 A
0:
b11 3
b0 &
b0 E
b10 2
1#
#250000
0#
#255000
05
b100 3
b1010 '
b1010 @
b11 2
1#
#260000
0#
#265000
b1 3
b100 2
1#
#270000
0#
#275000
b10 3
b110 9
b110 A
1:
b1 2
b110 1
b11110000 0
1#
#280000
0#
#285000
b110 4
b110 ;
15
b0 9
b0 A
0:
b11 3
b110 &
b110 E
b10 2
1#
#290000
0#
#295000
b0 4
b0 ;
05
b100 3
b1000110 '
b1000110 @
b11 2
1#
#300000
0#
#305000
b1 3
b100 2
1#
#310000
0#
#315000
b10 3
b111 9
b111 A
1:
b1 2
b111 1
b100110110 0
1#
#320000
0#
#325000
b100 4
b100 ;
15
b0 9
b0 A
0:
b11 3
b100 &
b100 E
b10 2
1#
#330000
0#
#335000
b0 4
b0 ;
05
b100 3
b110010 '
b110010 @
b11 2
1#
#340000
0#
#345000
b101 3
b100 2
1#
#350000
0#
#355000
b110 3
16
b101101000 7
b101101000 <
b1111 4
b1111 ;
15
b101 2
b1000 1
b101101000 0
1#
#360000
0#
#365000
b0 7
b0 <
b1111 4
b1111 ;
06
15
b111 3
b0 '
b0 @
b110 2
1#
#370000
0#
#375000
b0 4
b0 ;
05
b101101000 '
b101101000 @
b111 2
1#
#380000
0#
#385000
1"
b101101000 !
b101101000 8
1#
