Lab/verilog/assignment-3/half_adder.v
module half_adder(A, B, S, C);
  input A, B;
  output S, C;
  assign S = A ^ B;
  assign C = A & B;
endmodule

Lab/verilog/assignment-3/full_adder.v
module full_adder(A, B, Cin, S, Cout);
  input A, B, Cin;
  output S, Cout;

  wire inter_sum_1, inter_carry_1;
  wire placeholder, inter_carry_2;

  half_adder h1(
    .A(A),
    .B(B),
    .S(inter_sum_1),
    .C(inter_carry_1)
  );

  half_adder h2(
    .A(inter_sum_1),
    .B(Cin),
    .S(S),
    .C(inter_carry_2)
  );

  half_adder h3(
    .A(inter_carry_1),
    .B(inter_carry_2),
    .S(Cout),
    .C(placehodler)
  );

endmodule

Lab/verilog/assignment-7/adder/ripple_carry_adder_5bit.v
module ripple_carry_adder_5bit(A, B, S);
  input [4:0] A, B;
  output [5:0] S;

  wire c1, c2, c3, c4;

  full_adder f1(
    .A(A[0]),
    .B(B[0]),
    .Cin(1'b0),
    .S(S[0]),
    .Cout(c1)
  );

  full_adder f2(
    .A(A[1]),
    .B(B[1]),
    .Cin(c1),
    .S(S[1]),
    .Cout(c2)
  );

  full_adder f3(
    .A(A[2]),
    .B(B[2]),
    .Cin(c2),
    .S(S[2]),
    .Cout(c3)
  );

  full_adder f4(
    .A(A[3]),
    .B(B[3]),
    .Cin(c3),
    .S(S[3]),
    .Cout(c4)
  );

  full_adder f5(
    .A(A[4]),
    .B(B[4]),
    .Cin(c4),
    .S(S[4]),
    .Cout(S[5])
  );
endmodule

Lab/verilog/assignment-3/carry_save_stage_4bit.v
module carry_save_stage_4bit(A, B, C, S, Cout);
  input [3:0] A, B, C;
  output [3:0] S, Cout;

  full_adder fa1(
    .A(A[0]),
    .B(B[0]),
    .Cin(C[0]),
    .S(S[0]),
    .Cout(Cout[0])
  );
  full_adder fa2(
    .A(A[1]),
    .B(B[1]),
    .Cin(C[1]),
    .S(S[1]),
    .Cout(Cout[1])
  );
  full_adder fa3(
    .A(A[2]),
    .B(B[2]),
    .Cin(C[2]),
    .S(S[2]),
    .Cout(Cout[2])
  );
  full_adder fa4(
    .A(A[3]),
    .B(B[3]),
    .Cin(C[3]),
    .S(S[3]),
    .Cout(Cout[3])
  );

endmodule

Lab/verilog/assignment-7/adder/carry_save_adder_3x4.v
module carry_save_adder_3x4(A, B, C, O);
  input [3:0] A, B, C;
  output [5:0] O;

  wire [3:0] S, Cout;

  carry_save_stage_4bit css(
    .A(A),
    .B(B),
    .C(C),
    .S(S),
    .Cout(Cout)
  );

  wire [4:0] S_ext, C_ext;
  assign S_ext = {1'b0, S};
  assign C_ext = {Cout, 1'b0};

  ripple_carry_adder_5bit rca(
    .A(S_ext),
    .B(C_ext),
    .S(O)
  );

endmodule

Lab/verilog/assignment-3/tb_carry_save_adder.v
`timescale 1ns/1ps

module tb_carry_save_adder;
  reg [3:0] A, B, C;
  wire [5:0] O;
  reg [5:0] expected;

  integer i;
  integer passed, failed;

  carry_save_adder_3x4 csa(
    .A(A),
    .B(B),
    .C(C),
    .O(O)
  );

  initial begin
    $dumpfile("csa.vcd");
    $dumpvars(0, tb_carry_save_adder);
    passed = 0;
    failed = 0;

    for(i = 0; i < 4096; i = i + 1) begin
      {A, B, C} = i;
      expected = {2'b00, A} + {2'b00, B} + {2'b00, C};
      #20;
      if(O == expected) begin
        passed = passed + 1;
      end
      else begin
        failed++;
      end
    end
    $display("Passed: %d\nFailed: %d", passed, failed);
    $finish;
  end
endmodule

Lab/verilog/assignment-3/csa.vcd
$date
	Sun Sep 13 18:38:15 2026
$end
$version
	Icarus Verilog
$end
$timescale
	1ps
$end
$scope module tb_carry_save_adder $end
$var wire 6 ! O [5:0] $end
$var reg 4 " A [3:0] $end
$var reg 4 # B [3:0] $end
$var reg 4 $ C [3:0] $end
$var reg 6 % expected [5:0] $end
$var integer 32 & failed [31:0] $end
$var integer 32 ' i [31:0] $end
$var integer 32 ( passed [31:0] $end
$scope module csa $end
$var wire 4 ) A [3:0] $end
$var wire 4 * B [3:0] $end
$var wire 4 + C [3:0] $end
$var wire 5 , S_ext [4:0] $end
$var wire 4 - S [3:0] $end
$var wire 6 . O [5:0] $end
$var wire 4 / Cout [3:0] $end
$var wire 5 0 C_ext [4:0] $end
$scope module css $end
$var wire 4 1 A [3:0] $end
$var wire 4 2 B [3:0] $end
$var wire 4 3 C [3:0] $end
$var wire 4 4 S [3:0] $end
$var wire 4 5 Cout [3:0] $end
$scope module fa1 $end
$var wire 1 6 A $end
$var wire 1 7 B $end
$var wire 1 8 Cin $end
$var wire 1 9 placehodler $end
$var wire 1 : inter_sum_1 $end
$var wire 1 ; inter_carry_2 $end
$var wire 1 < inter_carry_1 $end
$var wire 1 = S $end
$var wire 1 > Cout $end
$scope module h1 $end
$var wire 1 6 A $end
$var wire 1 7 B $end
$var wire 1 < C $end
$var wire 1 : S $end
$upscope $end
$scope module h2 $end
$var wire 1 : A $end
$var wire 1 8 B $end
$var wire 1 ; C $end
$var wire 1 = S $end
$upscope $end
$scope module h3 $end
$var wire 1 < A $end
$var wire 1 ; B $end
$var wire 1 9 C $end
$var wire 1 > S $end
$upscope $end
$upscope $end
$scope module fa2 $end
$var wire 1 ? A $end
$var wire 1 @ B $end
$var wire 1 A Cin $end
$var wire 1 B placehodler $end
$var wire 1 C inter_sum_1 $end
$var wire 1 D inter_carry_2 $end
$var wire 1 E inter_carry_1 $end
$var wire 1 F S $end
$var wire 1 G Cout $end
$scope module h1 $end
$var wire 1 ? A $end
$var wire 1 @ B $end
$var wire 1 E C $end
$var wire 1 C S $end
$upscope $end
$scope module h2 $end
$var wire 1 C A $end
$var wire 1 A B $end
$var wire 1 D C $end
$var wire 1 F S $end
$upscope $end
$scope module h3 $end
$var wire 1 E A $end
$var wire 1 D B $end
$var wire 1 B C $end
$var wire 1 G S $end
$upscope $end
$upscope $end
$scope module fa3 $end
$var wire 1 H A $end
$var wire 1 I B $end
$var wire 1 J Cin $end
$var wire 1 K placehodler $end
$var wire 1 L inter_sum_1 $end
$var wire 1 M inter_carry_2 $end
$var wire 1 N inter_carry_1 $end
$var wire 1 O S $end
$var wire 1 P Cout $end
$scope module h1 $end
$var wire 1 H A $end
$var wire 1 I B $end
$var wire 1 N C $end
$var wire 1 L S $end
$upscope $end
$scope module h2 $end
$var wire 1 L A $end
$var wire 1 J B $end
$var wire 1 M C $end
$var wire 1 O S $end
$upscope $end
$scope module h3 $end
$var wire 1 N A $end
$var wire 1 M B $end
$var wire 1 K C $end
$var wire 1 P S $end
$upscope $end
$upscope $end
$scope module fa4 $end
$var wire 1 Q A $end
$var wire 1 R B $end
$var wire 1 S Cin $end
$var wire 1 T placehodler $end
$var wire 1 U inter_sum_1 $end
$var wire 1 V inter_carry_2 $end
$var wire 1 W inter_carry_1 $end
$var wire 1 X S $end
$var wire 1 Y Cout $end
$scope module h1 $end
$var wire 1 Q A $end
$var wire 1 R B $end
$var wire 1 W C $end
$var wire 1 U S $end
$upscope $end
$scope module h2 $end
$var wire 1 U A $end
$var wire 1 S B $end
$var wire 1 V C $end
$var wire 1 X S $end
$upscope $end
$scope module h3 $end
$var wire 1 W A $end
$var wire 1 V B $end
$var wire 1 T C $end
$var wire 1 Y S $end
$upscope $end
$upscope $end
$upscope $end
$scope module rca $end
$var wire 5 Z A [4:0] $end
$var wire 5 [ B [4:0] $end
$var wire 1 \ c4 $end
$var wire 1 ] c3 $end
$var wire 1 ^ c2 $end
$var wire 1 _ c1 $end
$var wire 6 ` S [5:0] $end
$scope module f1 $end
$var wire 1 a A $end
$var wire 1 b B $end
$var wire 1 c Cin $end
$var wire 1 d placehodler $end
$var wire 1 e inter_sum_1 $end
$var wire 1 f inter_carry_2 $end
$var wire 1 g inter_carry_1 $end
$var wire 1 h S $end
$var wire 1 _ Cout $end
$scope module h1 $end
$var wire 1 a A $end
$var wire 1 b B $end
$var wire 1 g C $end
$var wire 1 e S $end
$upscope $end
$scope module h2 $end
$var wire 1 e A $end
$var wire 1 c B $end
$var wire 1 f C $end
$var wire 1 h S $end
$upscope $end
$scope module h3 $end
$var wire 1 g A $end
$var wire 1 f B $end
$var wire 1 d C $end
$var wire 1 _ S $end
$upscope $end
$upscope $end
$scope module f2 $end
$var wire 1 i A $end
$var wire 1 j B $end
$var wire 1 _ Cin $end
$var wire 1 k placehodler $end
$var wire 1 l inter_sum_1 $end
$var wire 1 m inter_carry_2 $end
$var wire 1 n inter_carry_1 $end
$var wire 1 o S $end
$var wire 1 ^ Cout $end
$scope module h1 $end
$var wire 1 i A $end
$var wire 1 j B $end
$var wire 1 n C $end
$var wire 1 l S $end
$upscope $end
$scope module h2 $end
$var wire 1 l A $end
$var wire 1 _ B $end
$var wire 1 m C $end
$var wire 1 o S $end
$upscope $end
$scope module h3 $end
$var wire 1 n A $end
$var wire 1 m B $end
$var wire 1 k C $end
$var wire 1 ^ S $end
$upscope $end
$upscope $end
$scope module f3 $end
$var wire 1 p A $end
$var wire 1 q B $end
$var wire 1 ^ Cin $end
$var wire 1 r placehodler $end
$var wire 1 s inter_sum_1 $end
$var wire 1 t inter_carry_2 $end
$var wire 1 u inter_carry_1 $end
$var wire 1 v S $end
$var wire 1 ] Cout $end
$scope module h1 $end
$var wire 1 p A $end
$var wire 1 q B $end
$var wire 1 u C $end
$var wire 1 s S $end
$upscope $end
$scope module h2 $end
$var wire 1 s A $end
$var wire 1 ^ B $end
$var wire 1 t C $end
$var wire 1 v S $end
$upscope $end
$scope module h3 $end
$var wire 1 u A $end
$var wire 1 t B $end
$var wire 1 r C $end
$var wire 1 ] S $end
$upscope $end
$upscope $end
$scope module f4 $end
$var wire 1 w A $end
$var wire 1 x B $end
$var wire 1 ] Cin $end
$var wire 1 y placehodler $end
$var wire 1 z inter_sum_1 $end
$var wire 1 { inter_carry_2 $end
$var wire 1 | inter_carry_1 $end
$var wire 1 } S $end
$var wire 1 \ Cout $end
$scope module h1 $end
$var wire 1 w A $end
$var wire 1 x B $end
$var wire 1 | C $end
$var wire 1 z S $end
$upscope $end
$scope module h2 $end
$var wire 1 z A $end
$var wire 1 ] B $end
$var wire 1 { C $end
$var wire 1 } S $end
$upscope $end
$scope module h3 $end
$var wire 1 | A $end
$var wire 1 { B $end
$var wire 1 y C $end
$var wire 1 \ S $end
$upscope $end
$upscope $end
$scope module f5 $end
$var wire 1 ~ A $end
$var wire 1 !" B $end
$var wire 1 \ Cin $end
$var wire 1 "" placehodler $end
$var wire 1 #" inter_sum_1 $end
$var wire 1 $" inter_carry_2 $end
$var wire 1 %" inter_carry_1 $end
$var wire 1 &" S $end
$var wire 1 '" Cout $end
$scope module h1 $end
$var wire 1 ~ A $end
$var wire 1 !" B $end
$var wire 1 %" C $end
$var wire 1 #" S $end
$upscope $end
$scope module h2 $end
$var wire 1 #" A $end
$var wire 1 \ B $end
$var wire 1 $" C $end
$var wire 1 &" S $end
$upscope $end
$scope module h3 $end
$var wire 1 %" A $end
$var wire 1 $" B $end
$var wire 1 "" C $end
$var wire 1 '" S $end
$upscope $end
$upscope $end
$upscope $end
$upscope $end
$upscope $end
$enddefinitions $end
$comment Show the parameter values. $end
$dumpall
$end
#0
$dumpvars
0'"
0&"
0%"
0$"
0#"
0""
0!"
0~
0}
0|
0{
0z
0y
0x
0w
0v
0u
0t
0s
0r
0q
0p
0o
0n
0m
0l
0k
0j
0i
0h
0g
0f
0e
0d
0c
0b
0a
b0 `
0_
0^
0]
0\
b0 [
b0 Z
0Y
0X
0W
0V
0U
0T
0S
0R
0Q
0P
0O
0N
0M
0L
0K
0J
0I
0H
0G
0F
0E
0D
0C
0B
0A
0@
0?
0>
0=
0<
0;
0:
09
08
07
06
b0 5
b0 4
b0 3
b0 2
b0 1
b0 0
b0 /
b0 .
b0 -
b0 ,
b0 +
b0 *
b0 )
b0 (
b0 '
b0 &
b0 %
b0 $
b0 #
b0 "
b0 !
$end
#20000
b1 !
b1 .
b1 `
1h
1e
1a
b1 ,
b1 Z
b1 -
b1 4
1=
18
b1 %
b1 $
b1 +
b1 3
b1 '
b1 (
#40000
b10 !
b10 .
b10 `
0h
1o
0e
1l
0a
1i
b10 ,
b10 Z
b10 -
b10 4
0=
1F
08
1A
b10 %
b10 $
b10 +
b10 3
b10 '
b10 (
#60000
b11 !
b11 .
b11 `
1h
1e
1a
b11 ,
b11 Z
b11 -
b11 4
1=
18
b11 %
b11 $
b11 +
b11 3
b11 '
b11 (
#80000
b100 !
b100 .
b100 `
0h
0o
1v
0e
0l
1s
0a
0i
1p
b100 ,
b100 Z
b100 -
b100 4
0=
0F
1O
08
0A
1J
b100 %
b100 $
b100 +
b100 3
b100 '
b100 (
#100000
b101 !
b101 .
b101 `
1h
1e
1a
b101 ,
b101 Z
b101 -
b101 4
1=
18
b101 %
b101 $
b101 +
b101 3
b101 '
b101 (
#120000
b110 !
b110 .
b110 `
0h
1o
0e
1l
0a
1i
b110 ,
b110 Z
b110 -
b110 4
0=
1F
08
1A
b110 %
b110 $
b110 +
b110 3
b110 '
b110 (
#140000
b111 !
b111 .
b111 `
1h
1e
1a
b111 ,
b111 Z
b111 -
b111 4
1=
18
b111 %
b111 $
b111 +
b111 3
b111 '
b111 (
#160000
b1000 !
b1000 .
b1000 `
0h
0o
0v
1}
0e
0l
0s
1z
0a
0i
0p
1w
b1000 ,
b1000 Z
b1000 -
b1000 4
0=
0F
0O
1X
08
0A
0J
1S
b1000 %
b1000 $
b1000 +
b1000 3
b1000 '
b1000 (
#180000
b1001 !
b1001 .
b1001 `
1h
1e
1a
b1001 ,
b1001 Z
b1001 -
b1001 4
1=
18
b1001 %
b1001 $
b1001 +
b1001 3
b1001 '
b1001 (
#200000
b1010 !
b1010 .
b1010 `
0h
1o
0e
1l
0a
1i
b1010 ,
b1010 Z
b1010 -
b1010 4
0=
1F
08
1A
b1010 %
b1010 $
b1010 +
b1010 3
b1010 '
b1010 (
#220000
b1011 !
b1011 .
b1011 `
1h
1e
1a
b1011 ,
b1011 Z
b1011 -
b1011 4
1=
18
b1011 %
b1011 $
b1011 +
b1011 3
b1011 '
b1011 (
#240000
b1100 !
b1100 .
b1100 `
0h
0o
1v
0e
0l
1s
0a
0i
1p
b1100 ,
b1100 Z
b1100 -
b1100 4
0=
0F
1O
08
0A
1J
b1100 %
b1100 $
b1100 +
b1100 3
b1100 '
b1100 (
#260000
b1101 !
b1101 .
b1101 `
1h
1e
1a
b1101 ,
b1101 Z
b1101 -
b1101 4
1=
18
b1101 %
b1101 $
b1101 +
b1101 3
b1101 '
b1101 (
#280000
b1110 !
b1110 .
b1110 `
0h
1o
0e
1l
0a
1i
b1110 ,
b1110 Z
b1110 -
b1110 4
0=
1F
08
1A
b1110 %
b1110 $
b1110 +
b1110 3
b1110 '
b1110 (
#300000
b1111 !
b1111 .
b1111 `
1h
1e
1a
b1111 ,
b1111 Z
b1111 -
b1111 4
1=
18
b1111 %
b1111 $
b1111 +
b1111 3
b1111 '
b1111 (
#320000
b1 !
b1 .
b1 `
1h
0o
0v
0}
1e
0l
0s
0z
1a
0i
0p
0w
b1 ,
b1 Z
b1 -
b1 4
1:
1=
0F
0O
0X
17
08
0A
0J
0S
b1 %
b1 #
b1 *
b1 2
b0 $
b0 +
b0 3
b10000 '
b10000 (
#340000
b10 !
b10 .
b10 `
1o
0h
1l
0e
1j
0a
b10 0
b10 [
b0 ,
b0 Z
b1 /
b1 5
b0 -
b0 4
1>
0=
1;
18
b10 %
b1 $
b1 +
b1 3
b10001 '
b10001 (
#360000
b11 !
b11 .
b11 `
0v
1h
1o
0^
0j
1e
1l
0n
b0 0
b0 [
1a
1i
b0 /
b0 5
b11 ,
b11 Z
0>
b11 -
b11 4
1=
0;
1F
08
1A
b11 %
b10 $
b10 +
b10 3
b10010 '
b10010 (
#380000
b100 !
b100 .
b100 `
1v
0o
1^
0h
0l
1n
0e
1j
0a
b10 0
b10 [
b10 ,
b10 Z
b1 /
b1 5
b10 -
b10 4
1>
0=
1;
18
b100 %
b11 $
b11 +
b11 3
b10011 '
b10011 (
#400000
b101 !
b101 .
b101 `
0}
0]
1h
0o
0^
1v
0t
0j
1e
0l
0n
1s
b0 0
b0 [
1a
0i
1p
b0 /
b0 5
b101 ,
b101 Z
0>
b101 -
b101 4
1=
0;
0F
1O
08
0A
1J
b101 %
b100 $
b100 +
b100 3
b10100 '
b10100 (
#420000
b110 !
b110 .
b110 `
1o
0h
1l
0e
1j
0a
b10 0
b10 [
b100 ,
b100 Z
b1 /
b1 5
b100 -
b100 4
1>
0=
1;
18
b110 %
b101 $
b101 +
b101 3
b10101 '
b10101 (
#440000
0}
b111 !
b111 .
b111 `
0]
1v
0t
1h
1o
0^
0j
1e
1l
0n
b0 0
b0 [
1a
1i
b0 /
b0 5
b111 ,
b111 Z
0>
b111 -
b111 4
1=
0;
1F
08
1A
b111 %
b110 $
b110 +
b110 3
b10110 '
b10110 (
#460000
1}
1]
b1000 !
b1000 .
b1000 `
0v
1t
0o
1^
0h
0l
1n
0e
1j
0a
b10 0
b10 [
b110 ,
b110 Z
b1 /
b1 5
b110 -
b110 4
1>
0=
1;
18
b1000 %
b111 $
b111 +
b111 3
b10111 '
b10111 (
#480000
b1001 !
b1001 .
b1001 `
0&"
0]
0\
1h
0o
0^
0v
0t
1}
0{
0j
1e
0l
0n
0s
1z
b0 0
b0 [
1a
0i
0p
1w
b0 /
b0 5
b1001 ,
b1001 Z
0>
b1001 -
b1001 4
1=
0;
0F
0O
1X
08
0A
0J
1S
b1001 %
b1000 $
b1000 +
b1000 3
b11000 '
b11000 (
#500000
b1010 !
b1010 .
b1010 `
1o
0h
1l
0e
1j
0a
b10 0
b10 [
b1000 ,
b1000 Z
b1 /
b1 5
b1000 -
b1000 4
1>
0=
1;
18
b1010 %
b1001 $
b1001 +
b1001 3
b11001 '
b11001 (
#520000
b1011 !
b1011 .
b1011 `
0v
1h
1o
0^
0j
1e
1l
0n
b0 0
b0 [
1a
1i
b0 /
b0 5
b1011 ,
b1011 Z
0>
b1011 -
b1011 4
1=
0;
1F
08
1A
b1011 %
b1010 $
b1010 +
b1010 3
b11010 '
b11010 (
#540000
b1100 !
b1100 .
b1100 `
1v
0o
1^
0h
0l
1n
0e
1j
0a
b10 0
b10 [
b1010 ,
b1010 Z
b1 /
b1 5
b1010 -
b1010 4
1>
0=
1;
18
b1100 %
b1011 $
b1011 +
b1011 3
b11011 '
b11011 (
#560000
0&"
0\
b1101 !
b1101 .
b1101 `
1}
0{
0]
1h
0o
0^
1v
0t
0j
1e
0l
0n
1s
b0 0
b0 [
1a
0i
1p
b0 /
b0 5
b1101 ,
b1101 Z
0>
b1101 -
b1101 4
1=
0;
0F
1O
08
0A
1J
b1101 %
b1100 $
b1100 +
b1100 3
b11100 '
b11100 (
#580000
b1110 !
b1110 .
b1110 `
1o
0h
1l
0e
1j
0a
b10 0
b10 [
b1100 ,
b1100 Z
b1 /
b1 5
b1100 -
b1100 4
1>
0=
1;
18
b1110 %
b1101 $
b1101 +
b1101 3
b11101 '
b11101 (
#600000
0&"
0\
1}
0{
b1111 !
b1111 .
b1111 `
0]
1v
0t
1h
1o
0^
0j
1e
1l
0n
b0 0
b0 [
1a
1i
b0 /
b0 5
b1111 ,
b1111 Z
0>
b1111 -
b1111 4
1=
0;
1F
08
1A
b1111 %
b1110 $
b1110 +
b1110 3
b11110 '
b11110 (
#620000
1&"
1\
0}
1{
1]
b10000 !
b10000 .
b10000 `
0v
1t
0o
1^
0h
0l
1n
0e
1j
0a
b10 0
b10 [
b1110 ,
b1110 Z
b1 /
b1 5
b1110 -
b1110 4
1>
0=
1;
18
b10000 %
b1111 $
b1111 +
b1111 3
b11111 '
b11111 (
#640000
b10 !
b10 .
b10 `
0&"
0]
0\
0h
1o
0^
0v
0t
0}
0{
0j
0e
1l
0n
0s
0z
b0 0
b0 [
0a
1i
0p
0w
b0 /
b0 5
b10 ,
b10 Z
0>
b10 -
b10 4
0:
1C
0=
0;
1F
0O
0X
07
1@
08
0A
0J
0S
b10 %
b10 #
b10 *
b10 2
b0 $
b0 +
b0 3
b100000 '
b100000 (
#660000
b11 !
b11 .
b11 `
1h
1e
1a
b11 ,
b11 Z
b11 -
b11 4
1=
18
b11 %
b1 $
b1 +
b1 3
b100001 '
b100001 (
#680000
b100 !
b100 .
b100 `
1v
0h
0o
1s
0e
0l
1q
0a
0i
b100 0
b100 [
b0 ,
b0 Z
b10 /
b10 5
b0 -
b0 4
1G
0=
0F
1D
08
1A
b100 %
b10 $
b10 +
b10 3
b100010 '
b100010 (
#700000
b101 !
b101 .
b101 `
1h
1e
1a
b1 ,
b1 Z
b1 -
b1 4
1=
18
b101 %
b11 $
b11 +
b11 3
b100011 '
b100011 (
#720000
b110 !
b110 .
b110 `
0}
0h
1o
1v
0]
0q
0e
1l
1s
0u
b0 0
b0 [
0a
1i
1p
b0 /
b0 5
b110 ,
b110 Z
0G
b110 -
b110 4
0=
1F
0D
1O
08
0A
1J
b110 %
b100 $
b100 +
b100 3
b100100 '
b100100 (
#740000
b111 !
b111 .
b111 `
1h
1e
1a
b111 ,
b111 Z
b111 -
b111 4
1=
18
b111 %
b101 $
b101 +
b101 3
b100101 '
b100101 (
#760000
b1000 !
b1000 .
b1000 `
1}
0v
1]
0h
0o
0s
1u
0e
0l
1q
0a
0i
b100 0
b100 [
b100 ,
b100 Z
b10 /
b10 5
b100 -
b100 4
1G
0=
0F
1D
08
1A
b1000 %
b110 $
b110 +
b110 3
b100110 '
b100110 (
#780000
b1001 !
b1001 .
b1001 `
1h
1e
1a
b101 ,
b101 Z
b101 -
b101 4
1=
18
b1001 %
b111 $
b111 +
b111 3
b100111 '
b100111 (
#800000
b1010 !
b1010 .
b1010 `
0&"
0\
0h
1o
0v
0]
1}
0{
0q
0e
1l
0s
0u
1z
b0 0
b0 [
0a
1i
0p
1w
b0 /
b0 5
b1010 ,
b1010 Z
0G
b1010 -
b1010 4
0=
1F
0D
0O
1X
08
0A
0J
1S
b1010 %
b1000 $
b1000 +
b1000 3
b101000 '
b101000 (
#820000
b1011 !
b1011 .
b1011 `
1h
1e
1a
b1011 ,
b1011 Z
b1011 -
b1011 4
1=
18
b1011 %
b1001 $
b1001 +
b1001 3
b101001 '
b101001 (
#840000
b1100 !
b1100 .
b1100 `
1v
0h
0o
1s
0e
0l
1q
0a
0i
b100 0
b100 [
b1000 ,
b1000 Z
b10 /
b10 5
b1000 -
b1000 4
1G
0=
0F
1D
08
1A
b1100 %
b1010 $
b1010 +
b1010 3
b101010 '
b101010 (
#860000
b1101 !
b1101 .
b1101 `
1h
1e
1a
b1001 ,
b1001 Z
b1001 -
b1001 4
1=
18
b1101 %
b1011 $
b1011 +
b1011 3
b101011 '
b101011 (
#880000
0&"
b1110 !
b1110 .
b1110 `
0\
1}
0{
0h
1o
1v
0]
0q
0e
1l
1s
0u
b0 0
b0 [
0a
1i
1p
b0 /
b0 5
b1110 ,
b1110 Z
0G
b1110 -
b1110 4
0=
1F
0D
1O
08
0A
1J
b1110 %
b1100 $
b1100 +
b1100 3
b101100 '
b101100 (
#900000
b1111 !
b1111 .
b1111 `
1h
1e
1a
b1111 ,
b1111 Z
b1111 -
b1111 4
1=
18
b1111 %
b1101 $
b1101 +
b1101 3
b101101 '
b101101 (
#920000
1&"
1\
b10000 !
b10000 .
b10000 `
0}
1{
0v
1]
0h
0o
0s
1u
0e
0l
1q
0a
0i
b100 0
b100 [
b1100 ,
b1100 Z
b10 /
b10 5
b1100 -
b1100 4
1G
0=
0F
1D
08
1A
b10000 %
b1110 $
b1110 +
b1110 3
b101110 '
b101110 (
#940000
b10001 !
b10001 .
b10001 `
1h
1e
1a
b1101 ,
b1101 Z
b1101 -
b1101 4
1=
18
b10001 %
b1111 $
b1111 +
b1111 3
b101111 '
b101111 (
#960000
b11 !
b11 .
b11 `
0&"
0\
1h
1o
0v
0]
0}
0{
0q
1e
1l
0s
0u
0z
b0 0
b0 [
1a
1i
0p
0w
b0 /
b0 5
b11 ,
b11 Z
0G
b11 -
b11 4
1:
1=
1F
0D
0O
0X
17
08
0A
0J
0S
b11 %
b11 #
b11 *
b11 2
b0 $
b0 +
b0 3
b110000 '
b110000 (
#980000
b100 !
b100 .
b100 `
1v
0o
1^
0h
0l
1n
0e
1j
0a
b10 0
b10 [
b10 ,
b10 Z
b1 /
b1 5
b10 -
b10 4
1>
0=
1;
18
b100 %
b1 $
b1 +
b1 3
b110001 '
b110001 (
#1000000
b101 !
b101 .
b101 `
1h
0^
1s
1e
0n
0j
1q
1a
0i
b100 0
b100 [
b1 ,
b1 Z
b10 /
b10 5
0>
b1 -
b1 4
1G
1=
0;
0F
1D
08
1A
b101 %
b10 $
b10 +
b10 3
b110010 '
b110010 (
#1020000
b110 !
b110 .
b110 `
1o
0h
1l
0e
1j
0a
b110 0
b110 [
b0 ,
b0 Z
b11 /
b11 5
b0 -
b0 4
1>
0=
1;
18
b110 %
b11 $
b11 +
b11 3
b110011 '
b110011 (
#1040000
b111 !
b111 .
b111 `
0t
0}
1h
1o
0^
1v
0]
0j
0q
1e
1l
0n
1s
0u
b0 0
b0 [
1a
1i
1p
b0 /
b0 5
b111 ,
b111 Z
0>
0G
b111 -
b111 4
1=
0;
1F
0D
1O
08
0A
1J
b111 %
b100 $
b100 +
b100 3
b110100 '
b110100 (
#1060000
1}
1]
b1000 !
b1000 .
b1000 `
0v
1t
0o
1^
0h
0l
1n
0e
1j
0a
b10 0
b10 [
b110 ,
b110 Z
b1 /
b1 5
b110 -
b110 4
1>
0=
1;
18
b1000 %
b101 $
b101 +
b101 3
b110101 '
b110101 (
#1080000
b1001 !
b1001 .
b1001 `
1}
0t
1]
0r
1h
0^
0s
1u
1e
0n
0j
1q
1a
0i
b100 0
b100 [
b101 ,
b101 Z
b10 /
b10 5
0>
b101 -
b101 4
1G
1=
0;
0F
1D
08
1A
b1001 %
b110 $
b110 +
b110 3
b110110 '
b110110 (
#1100000
b1010 !
b1010 .
b1010 `
1o
0h
1l
0e
1j
0a
b110 0
b110 [
b100 ,
b100 Z
b11 /
b11 5
b100 -
b100 4
1>
0=
1;
18
b1010 %
b111 $
b111 +
b111 3
b110111 '
b110111 (
#1120000
b1011 !
b1011 .
b1011 `
0&"
0\
1h
1o
0^
0v
0]
1}
0{
0j
0q
1e
1l
0n
0s
0u
1z
b0 0
b0 [
1a
1i
0p
1w
b0 /
b0 5
b1011 ,
b1011 Z
0>
0G
b1011 -
b1011 4
1=
0;
1F
0D
0O
1X
08
0A
0J
1S
b1011 %
b1000 $
b1000 +
b1000 3
b111000 '
b111000 (
#1140000
b1100 !
b1100 .
b1100 `
1v
0o
1^
0h
0l
1n
0e
1j
0a
b10 0
b10 [
b1010 ,
b1010 Z
b1 /
b1 5
b1010 -
b1010 4
1>
0=
1;
18
b1100 %
b1001 $
b1001 +
b1001 3
b111001 '
b111001 (
#1160000
b1101 !
b1101 .
b1101 `
1h
0^
1s
1e
0n
0j
1q
1a
0i
b100 0
b100 [
b1001 ,
b1001 Z
b10 /
b10 5
0>
b1001 -
b1001 4
1G
1=
0;
0F
1D
08
1A
b1101 %
b1010 $
b1010 +
b1010 3
b111010 '
b111010 (
#1180000
b1110 !
b1110 .
b1110 `
1o
0h
1l
0e
1j
0a
b110 0
b110 [
b1000 ,
b1000 Z
b11 /
b11 5
b1000 -
b1000 4
1>
0=
1;
18
b1110 %
b1011 $
b1011 +
b1011 3
b111011 '
b111011 (
#1200000
0&"
b1111 !
b1111 .
b1111 `
0\
0t
1}
0{
1h
1o
0^
1v
0]
0j
0q
1e
1l
0n
1s
0u
b0 0
b0 [
1a
1i
1p
b0 /
b0 5
b1111 ,
b1111 Z
0>
0G
b1111 -
b1111 4
1=
0;
1F
0D
1O
08
0A
1J
b1111 %
b1100 $
b1100 +
b1100 3
b111100 '
b111100 (
#1220000
1&"
1\
0}
1{
1]
b10000 !
b10000 .
b10000 `
0v
1t
0o
1^
0h
0l
1n
0e
1j
0a
b10 0
b10 [
b1110 ,
b1110 Z
b1 /
b1 5
b1110 -
b1110 4
1>
0=
1;
18
b10000 %
b1101 $
b1101 +
b1101 3
b111101 '
b111101 (
#1240000
1&"
1\
b10001 !
b10001 .
b10001 `
0}
1{
0t
1]
0r
1h
0^
0s
1u
1e
0n
0j
1q
1a
0i
b100 0
b100 [
b1101 ,
b1101 Z
b10 /
b10 5
0>
b1101 -
b1101 4
1G
1=
0;
0F
1D
08
1A
b10001 %
b1110 $
b1110 +
b1110 3
b111110 '
b111110 (
#1260000
b10010 !
b10010 .
b10010 `
1o
0h
1l
0e
1j
0a
b110 0
b110 [
b1100 ,
b1100 Z
b11 /
b11 5
b1100 -
b1100 4
1>
0=
1;
18
b10010 %
b1111 $
b1111 +
b1111 3
b111111 '
b111111 (
#1280000
b100 !
b100 .
b100 `
0&"
0t
0\
0h
0o
0^
1v
0]
0}
0{
0j
0q
0e
0l
0n
1s
0u
0z
b0 0
b0 [
0a
0i
1p
0w
b0 /
b0 5
b100 ,
b100 Z
0>
0G
b100 -
b100 4
0:
0C
1L
0=
0;
0F
0D
1O
0X
07
0@
1I
08
0A
0J
0S
b100 %
b100 #
b100 *
b100 2
b0 $
b0 +
b0 3
b1000000 '
b1000000 (
#1300000
b101 !
b101 .
b101 `
1h
1e
1a
b101 ,
b101 Z
b101 -
b101 4
1=
18
b101 %
b1 $
b1 +
b1 3
b1000001 '
b1000001 (
#1320000
b110 !
b110 .
b110 `
0h
1o
0e
1l
0a
1i
b110 ,
b110 Z
b110 -
b110 4
0=
1F
08
1A
b110 %
b10 $
b10 +
b10 3
b1000010 '
b1000010 (
