Lab/verilog/assignment-1/mux_4to1_5bit.v
module mux_4to1_5bit(I0, I1, I2, I3, sel, Y);
  input [4:0] I0, I1, I2, I3;
  input [1:0] sel;
  output reg [4:0] Y;

  always @(*) begin
    case(sel)
      2'b00: begin
        Y = I0;
      end
      2'b01: begin
        Y = I1;
      end
      2'b10: begin
        Y = I2;
      end
      2'b11: begin
        Y = I3;
      end
      default: begin
        Y = 5'b0;
      end
    endcase
  end

endmodule

Lab/verilog/assignment-1/bitwise_modules.v
module and_4bit(A, B, Out);
  input [3:0] A, B;
  output [4:0] Out;

  assign Out[0] = A[0] & B[0];
  assign Out[1] = A[1] & B[1];
  assign Out[2] = A[2] & B[2];
  assign Out[3] = A[3] & B[3];
  assign Out[4] = 1'b0;
endmodule


module or_4bit(A, B, Out);
  input [3:0] A, B;
  output [4:0] Out;

  assign Out[0] = A[0] | B[0];
  assign Out[1] = A[1] | B[1];
  assign Out[2] = A[2] | B[2];
  assign Out[3] = A[3] | B[3];
  assign Out[4] = 1'b0;
endmodule

module xor_4bit(A, B, Out);
  input [3:0] A, B;
  output [4:0] Out;

  assign Out[0] = A[0] ^ B[0];
  assign Out[1] = A[1] ^ B[1];
  assign Out[2] = A[2] ^ B[2];
  assign Out[3] = A[3] ^ B[3];
  assign Out[4] = 1'b0;
endmodule

Lab/verilog/assignment-1/half_adder.v
module half_adder(A, B, S, C);
  input A, B;
  output S, C;
endmodule

Lab/verilog/assignment-3/full_adder.v
module full_adder(A, B, Cin, S, Cout);
  input A, B, Cin;
  output S, Cout;

  wire inter_sum_1, inter_carry_1;
  wire placeholder, inter_carry_2;

  half_adder h1(
    .A(A),
    .B(B),
    .S(inter_sum_1),
    .C(inter_carry_1)
  );

  half_adder h2(
    .A(inter_sum_1),
    .B(Cin),
    .S(S),
    .C(inter_carry_2)
  );

  half_adder h3(
    .A(inter_carry_1),
    .B(inter_carry_2),
    .S(Cout),
    .C(placehodler)
  );

endmodule

Lab/verilog/assignment-1/ripple_carry_adder_4bit.v
module ripple_carry_adder_4bit(A, B, S);
  input [3:0] A, B;
  output [4:0] S;

  wire c1, c2, c3;

  full_adder f1(
    .A(A[0]),
    .B(B[0]),
    .Cin(1'b0),
    .S(S[0]),
    .Cout(c1)
  );

  full_adder f2(
    .A(A[1]),
    .B(B[1]),
    .Cin(c1),
    .S(S[1]),
    .Cout(c2)
  );

  full_adder f3(
    .A(A[2]),
    .B(B[2]),
    .Cin(c2),
    .S(S[2]),
    .Cout(c3)
  );

  full_adder f4(
    .A(A[3]),
    .B(B[3]),
    .Cin(c3),
    .S(S[3]),
    .Cout(S[4])
  );
endmodule

Lab/verilog/assignment-1/logic_unit.v
module logic_unit(A, B, sel, Y);
  input [3:0] A, B;
  input [1:0] sel;
  output [4:0] Y;

  wire [4:0] I0, I1, I2, I3;
  ripple_carry_adder_4bit rca(
    .A(A),
    .B(B),
    .S(I0)
  );
  and_4bit a(
    .A(A),
    .B(B),
    .Out(I1)
  );
  or_4bit o(
    .A(A),
    .B(B),
    .Out(I2)
  );
  xor_4bit x(
    .A(A),
    .B(B),
    .Out(I3)
  );

  mux_4to1_5bit mux1(
    .I0(I0),
    .I1(I1),
    .I2(I2),
    .I3(I3),
    .sel(sel),
    .Y(Y)
  );

endmodule

Lab/verilog/assignment-1/tb_logic_unit.v
`timescale 1ns/1ps

module tb_logic_unit;
  reg [3:0] A, B;
  reg [1:0] sel;
  reg [4:0] expected;
  wire [4:0] Y;

  integer i;
  integer passed, failed;

  logic_unit alu(
    .A(A),
    .B(B),
    .sel(sel),
    .Y(Y)
  );

  initial begin
    $dumpfile("logic_sim.vcd");
    $dumpvars(0, tb_logic_unit);

    passed = 0;
    failed = 0;

    sel = 2'b00;
    for(i = 0; i <= 8'b11111111; i = i + 1) begin
      {A, B} = i;
      expected = A + B;
      #20;
      if (Y == expected) begin
        passed = passed + 1;
      end
      else begin
        failed = failed + 1;
      end
    end

    sel = 2'b01;
    for(i = 0; i <= 8'b11111111; i = i + 1) begin
      {A, B} = i;
      expected = A & B;
      #20;
      if (Y == expected) begin
        passed = passed + 1;
      end
      else begin
        failed = failed + 1;
      end
    end

    sel = 2'b10;
    for(i = 0; i <= 8'b11111111; i = i + 1) begin
      {A, B} = i;
      expected = A | B;
      #20;
      if (Y == expected) begin
        passed = passed + 1;
      end
      else begin
        failed = failed + 1;
      end
    end

    sel = 2'b11;
    for(i = 0; i <= 8'b11111111; i = i + 1) begin
      {A, B} = i;
      expected = A ^ B;
      #20;
      if (Y == expected) begin
        passed = passed + 1;
      end
      else begin
        failed = failed + 1;
      end
    end

    $display("Passed: %d;\tFailed: %d;", passed, failed);

  end
endmodule

Lab/verilog/assignment-1/logic_sim.vcd
$date
	Sun Sep 13 16:46:14 2026
$end
$version
	Icarus Verilog
$end
$timescale
	1ps
$end
$scope module tb_logic_unit $end
$var wire 5 ! Y [4:0] $end
$var reg 4 " A [3:0] $end
$var reg 4 # B [3:0] $end
$var reg 5 $ expected [4:0] $end
$var reg 2 % sel [1:0] $end
$var integer 32 & failed [31:0] $end
$var integer 32 ' i [31:0] $end
$var integer 32 ( passed [31:0] $end
$scope module alu $end
$var wire 4 ) A [3:0] $end
$var wire 4 * B [3:0] $end
$var wire 2 + sel [1:0] $end
$var wire 5 , Y [4:0] $end
$var wire 5 - I3 [4:0] $end
$var wire 5 . I2 [4:0] $end
$var wire 5 / I1 [4:0] $end
$var wire 5 0 I0 [4:0] $end
$scope module a $end
$var wire 4 1 A [3:0] $end
$var wire 4 2 B [3:0] $end
$var wire 5 3 Out [4:0] $end
$upscope $end
$scope module mux1 $end
$var wire 5 4 I1 [4:0] $end
$var wire 2 5 sel [1:0] $end
$var wire 5 6 I3 [4:0] $end
$var wire 5 7 I2 [4:0] $end
$var wire 5 8 I0 [4:0] $end
$var reg 5 9 Y [4:0] $end
$upscope $end
$scope module o $end
$var wire 4 : A [3:0] $end
$var wire 4 ; B [3:0] $end
$var wire 5 < Out [4:0] $end
$upscope $end
$scope module rca $end
$var wire 4 = A [3:0] $end
$var wire 4 > B [3:0] $end
$var wire 1 ? c3 $end
$var wire 1 @ c2 $end
$var wire 1 A c1 $end
$var wire 5 B S [4:0] $end
$scope module f1 $end
$var wire 1 C A $end
$var wire 1 D B $end
$var wire 1 E Cin $end
$var wire 1 F placehodler $end
$var wire 1 G inter_sum_1 $end
$var wire 1 H inter_carry_2 $end
$var wire 1 I inter_carry_1 $end
$var wire 1 J S $end
$var wire 1 A Cout $end
$scope module h1 $end
$var wire 1 C A $end
$var wire 1 D B $end
$var wire 1 I C $end
$var wire 1 G S $end
$upscope $end
$scope module h2 $end
$var wire 1 G A $end
$var wire 1 E B $end
$var wire 1 H C $end
$var wire 1 J S $end
$upscope $end
$scope module h3 $end
$var wire 1 I A $end
$var wire 1 H B $end
$var wire 1 F C $end
$var wire 1 A S $end
$upscope $end
$upscope $end
$scope module f2 $end
$var wire 1 K A $end
$var wire 1 L B $end
$var wire 1 A Cin $end
$var wire 1 M placehodler $end
$var wire 1 N inter_sum_1 $end
$var wire 1 O inter_carry_2 $end
$var wire 1 P inter_carry_1 $end
$var wire 1 Q S $end
$var wire 1 @ Cout $end
$scope module h1 $end
$var wire 1 K A $end
$var wire 1 L B $end
$var wire 1 P C $end
$var wire 1 N S $end
$upscope $end
$scope module h2 $end
$var wire 1 N A $end
$var wire 1 A B $end
$var wire 1 O C $end
$var wire 1 Q S $end
$upscope $end
$scope module h3 $end
$var wire 1 P A $end
$var wire 1 O B $end
$var wire 1 M C $end
$var wire 1 @ S $end
$upscope $end
$upscope $end
$scope module f3 $end
$var wire 1 R A $end
$var wire 1 S B $end
$var wire 1 @ Cin $end
$var wire 1 T placehodler $end
$var wire 1 U inter_sum_1 $end
$var wire 1 V inter_carry_2 $end
$var wire 1 W inter_carry_1 $end
$var wire 1 X S $end
$var wire 1 ? Cout $end
$scope module h1 $end
$var wire 1 R A $end
$var wire 1 S B $end
$var wire 1 W C $end
$var wire 1 U S $end
$upscope $end
$scope module h2 $end
$var wire 1 U A $end
$var wire 1 @ B $end
$var wire 1 V C $end
$var wire 1 X S $end
$upscope $end
$scope module h3 $end
$var wire 1 W A $end
$var wire 1 V B $end
$var wire 1 T C $end
$var wire 1 ? S $end
$upscope $end
$upscope $end
$scope module f4 $end
$var wire 1 Y A $end
$var wire 1 Z B $end
$var wire 1 ? Cin $end
$var wire 1 [ placehodler $end
$var wire 1 \ inter_sum_1 $end
$var wire 1 ] inter_carry_2 $end
$var wire 1 ^ inter_carry_1 $end
$var wire 1 _ S $end
$var wire 1 ` Cout $end
$scope module h1 $end
$var wire 1 Y A $end
$var wire 1 Z B $end
$var wire 1 ^ C $end
$var wire 1 \ S $end
$upscope $end
$scope module h2 $end
$var wire 1 \ A $end
$var wire 1 ? B $end
$var wire 1 ] C $end
$var wire 1 _ S $end
$upscope $end
$scope module h3 $end
$var wire 1 ^ A $end
$var wire 1 ] B $end
$var wire 1 [ C $end
$var wire 1 ` S $end
$upscope $end
$upscope $end
$upscope $end
$scope module x $end
$var wire 4 a A [3:0] $end
$var wire 4 b B [3:0] $end
$var wire 5 c Out [4:0] $end
$upscope $end
$upscope $end
$upscope $end
$enddefinitions $end
$comment Show the parameter values. $end
$dumpall
$end
#0
$dumpvars
b0 c
b0 b
b0 a
0`
0_
0^
0]
0\
0[
0Z
0Y
0X
0W
0V
0U
0T
0S
0R
0Q
0P
0O
0N
0M
0L
0K
0J
0I
0H
0G
0F
0E
0D
0C
b0 B
0A
0@
0?
b0 >
b0 =
b0 <
b0 ;
b0 :
b0 9
b0 8
b0 7
b0 6
b0 5
b0 4
b0 3
b0 2
b0 1
b0 0
b0 /
b0 .
b0 -
b0 ,
b0 +
b0 *
b0 )
b0 (
b0 '
b0 &
b0 %
b0 $
b0 #
b0 "
b0 !
$end
#20000
b1 !
b1 ,
b1 9
b1 0
b1 8
b1 B
b1 .
b1 7
b1 <
b1 -
b1 6
b1 c
1J
1G
1D
b1 $
b1 #
b1 *
b1 2
b1 ;
b1 >
b1 b
b1 '
b1 (
#40000
b10 !
b10 ,
b10 9
b10 0
b10 8
b10 B
b10 .
b10 7
b10 <
b10 -
b10 6
b10 c
0J
1Q
0G
1N
0D
1L
b10 $
b10 #
b10 *
b10 2
b10 ;
b10 >
b10 b
b10 '
b10 (
#60000
b11 !
b11 ,
b11 9
b11 0
b11 8
b11 B
b11 .
b11 7
b11 <
b11 -
b11 6
b11 c
1J
1G
1D
b11 $
b11 #
b11 *
b11 2
b11 ;
b11 >
b11 b
b11 '
b11 (
#80000
b100 !
b100 ,
b100 9
b100 0
b100 8
b100 B
b100 .
b100 7
b100 <
b100 -
b100 6
b100 c
0J
0Q
1X
0G
0N
1U
0D
0L
1S
b100 $
b100 #
b100 *
b100 2
b100 ;
b100 >
b100 b
b100 '
b100 (
#100000
b101 !
b101 ,
b101 9
b101 0
b101 8
b101 B
b101 .
b101 7
b101 <
b101 -
b101 6
b101 c
1J
1G
1D
b101 $
b101 #
b101 *
b101 2
b101 ;
b101 >
b101 b
b101 '
b101 (
#120000
b110 !
b110 ,
b110 9
b110 0
b110 8
b110 B
b110 .
b110 7
b110 <
b110 -
b110 6
b110 c
0J
1Q
0G
1N
0D
1L
b110 $
b110 #
b110 *
b110 2
b110 ;
b110 >
b110 b
b110 '
b110 (
#140000
b111 !
b111 ,
b111 9
b111 0
b111 8
b111 B
b111 .
b111 7
b111 <
b111 -
b111 6
b111 c
1J
1G
1D
b111 $
b111 #
b111 *
b111 2
b111 ;
b111 >
b111 b
b111 '
b111 (
#160000
b1000 !
b1000 ,
b1000 9
b1000 0
b1000 8
b1000 B
b1000 .
b1000 7
b1000 <
b1000 -
b1000 6
b1000 c
0J
0Q
0X
1_
0G
0N
0U
1\
0D
0L
0S
1Z
b1000 $
b1000 #
b1000 *
b1000 2
b1000 ;
b1000 >
b1000 b
b1000 '
b1000 (
#180000
b1001 !
b1001 ,
b1001 9
b1001 0
b1001 8
b1001 B
b1001 .
b1001 7
b1001 <
b1001 -
b1001 6
b1001 c
1J
1G
1D
b1001 $
b1001 #
b1001 *
b1001 2
b1001 ;
b1001 >
b1001 b
b1001 '
b1001 (
#200000
b1010 !
b1010 ,
b1010 9
b1010 0
b1010 8
b1010 B
b1010 .
b1010 7
b1010 <
b1010 -
b1010 6
b1010 c
0J
1Q
0G
1N
0D
1L
b1010 $
b1010 #
b1010 *
b1010 2
b1010 ;
b1010 >
b1010 b
b1010 '
b1010 (
#220000
b1011 !
b1011 ,
b1011 9
b1011 0
b1011 8
b1011 B
b1011 .
b1011 7
b1011 <
b1011 -
b1011 6
b1011 c
1J
1G
1D
b1011 $
b1011 #
b1011 *
b1011 2
b1011 ;
b1011 >
b1011 b
b1011 '
b1011 (
#240000
b1100 !
b1100 ,
b1100 9
b1100 0
b1100 8
b1100 B
b1100 .
b1100 7
b1100 <
b1100 -
b1100 6
b1100 c
0J
0Q
1X
0G
0N
1U
0D
0L
1S
b1100 $
b1100 #
b1100 *
b1100 2
b1100 ;
b1100 >
b1100 b
b1100 '
b1100 (
#260000
b1101 !
b1101 ,
b1101 9
b1101 0
b1101 8
b1101 B
b1101 .
b1101 7
b1101 <
b1101 -
b1101 6
b1101 c
1J
1G
1D
b1101 $
b1101 #
b1101 *
b1101 2
b1101 ;
b1101 >
b1101 b
b1101 '
b1101 (
#280000
b1110 !
b1110 ,
b1110 9
b1110 0
b1110 8
b1110 B
b1110 .
b1110 7
b1110 <
b1110 -
b1110 6
b1110 c
0J
1Q
0G
1N
0D
1L
b1110 $
b1110 #
b1110 *
b1110 2
b1110 ;
b1110 >
b1110 b
b1110 '
b1110 (
#300000
b1111 !
b1111 ,
b1111 9
b1111 0
b1111 8
b1111 B
b1111 .
b1111 7
b1111 <
b1111 -
b1111 6
b1111 c
1J
1G
1D
b1111 $
b1111 #
b1111 *
b1111 2
b1111 ;
b1111 >
b1111 b
b1111 '
b1111 (
#320000
b1 !
b1 ,
b1 9
b1 0
b1 8
b1 B
b1 .
b1 7
b1 <
b1 -
b1 6
b1 c
0Q
0X
0_
0N
0U
0\
1C
0D
0L
0S
0Z
b1 $
b1 "
b1 )
b1 1
b1 :
b1 =
b1 a
b0 #
b0 *
b0 2
b0 ;
b0 >
b0 b
b10000 '
b10000 (
#340000
b10 !
b10 ,
b10 9
b10 0
b10 8
b10 B
b1 /
b1 3
b1 4
1Q
b0 -
b0 6
b0 c
0J
1A
0G
1I
1D
b10 $
b1 #
b1 *
b1 2
b1 ;
b1 >
b1 b
b10001 '
b10001 (
#360000
b11 !
b11 ,
b11 9
b11 0
b11 8
b11 B
0X
b0 /
b0 3
b0 4
b11 .
b11 7
b11 <
0@
b11 -
b11 6
b11 c
1J
0A
1Q
0O
1G
0I
1N
0D
1L
b11 $
b10 #
b10 *
b10 2
b10 ;
b10 >
b10 b
b10010 '
b10010 (
#380000
b100 !
b100 ,
b100 9
1X
b100 0
b100 8
b100 B
1@
b1 /
b1 3
b1 4
0Q
1O
b10 -
b10 6
b10 c
0J
1A
0G
1I
1D
b100 $
b11 #
b11 *
b11 2
b11 ;
b11 >
b11 b
b10011 '
b10011 (
#400000
b101 !
b101 ,
b101 9
b101 0
b101 8
b101 B
0_
b0 /
b0 3
b0 4
b101 .
b101 7
b101 <
0@
0?
b101 -
b101 6
b101 c
1J
0A
0Q
0O
1X
0V
1G
0I
0N
1U
0D
0L
1S
b101 $
b100 #
b100 *
b100 2
b100 ;
b100 >
b100 b
b10100 '
b10100 (
#420000
b110 !
b110 ,
b110 9
b110 0
b110 8
b110 B
b1 /
b1 3
b1 4
1Q
b100 -
b100 6
b100 c
0J
1A
0G
1I
1D
b110 $
b101 #
b101 *
b101 2
b101 ;
b101 >
b101 b
b10101 '
b10101 (
#440000
0_
b111 !
b111 ,
b111 9
0?
b111 0
b111 8
b111 B
1X
0V
b0 /
b0 3
b0 4
b111 .
b111 7
b111 <
0@
b111 -
b111 6
b111 c
1J
0A
1Q
0O
1G
0I
1N
0D
1L
b111 $
b110 #
b110 *
b110 2
b110 ;
b110 >
b110 b
b10110 '
b10110 (
#460000
1_
1?
b1000 !
b1000 ,
b1000 9
0X
1V
b1000 0
b1000 8
b1000 B
1@
b1 /
b1 3
b1 4
0Q
1O
b110 -
b110 6
b110 c
0J
1A
0G
1I
1D
b1000 $
b111 #
b111 *
b111 2
b111 ;
b111 >
b111 b
b10111 '
b10111 (
#480000
b1001 !
b1001 ,
b1001 9
b1001 0
b1001 8
b1001 B
b0 /
b0 3
b0 4
b1001 .
b1001 7
b1001 <
0@
0?
0`
b1001 -
b1001 6
b1001 c
1J
0A
0Q
0O
0X
0V
1_
0]
1G
0I
0N
0U
1\
0D
0L
0S
1Z
b1001 $
b1000 #
b1000 *
b1000 2
b1000 ;
b1000 >
b1000 b
b11000 '
b11000 (
#500000
b1010 !
b1010 ,
b1010 9
b1010 0
b1010 8
b1010 B
b1 /
b1 3
b1 4
1Q
b1000 -
b1000 6
b1000 c
0J
1A
0G
1I
1D
b1010 $
b1001 #
b1001 *
b1001 2
b1001 ;
b1001 >
b1001 b
b11001 '
b11001 (
#520000
b1011 !
b1011 ,
b1011 9
b1011 0
b1011 8
b1011 B
0X
b0 /
b0 3
b0 4
b1011 .
b1011 7
b1011 <
0@
b1011 -
b1011 6
b1011 c
1J
0A
1Q
0O
1G
0I
1N
0D
1L
b1011 $
b1010 #
b1010 *
b1010 2
b1010 ;
b1010 >
b1010 b
b11010 '
b11010 (
#540000
b1100 !
b1100 ,
b1100 9
1X
b1100 0
b1100 8
b1100 B
1@
b1 /
b1 3
b1 4
0Q
1O
b1010 -
b1010 6
b1010 c
0J
1A
0G
1I
1D
b1100 $
b1011 #
b1011 *
b1011 2
b1011 ;
b1011 >
b1011 b
b11011 '
b11011 (
#560000
b1101 !
b1101 ,
b1101 9
0`
b1101 0
b1101 8
b1101 B
1_
0]
b0 /
b0 3
b0 4
b1101 .
b1101 7
b1101 <
0@
0?
b1101 -
b1101 6
b1101 c
1J
0A
0Q
0O
1X
0V
1G
0I
0N
1U
0D
0L
1S
b1101 $
b1100 #
b1100 *
b1100 2
b1100 ;
b1100 >
b1100 b
b11100 '
b11100 (
#580000
b1110 !
b1110 ,
b1110 9
b1110 0
b1110 8
b1110 B
b1 /
b1 3
b1 4
1Q
b1100 -
b1100 6
b1100 c
0J
1A
0G
1I
1D
b1110 $
b1101 #
b1101 *
b1101 2
b1101 ;
b1101 >
b1101 b
b11101 '
b11101 (
#600000
0`
1_
0]
b1111 !
b1111 ,
b1111 9
0?
b1111 0
b1111 8
b1111 B
1X
0V
b0 /
b0 3
b0 4
b1111 .
b1111 7
b1111 <
0@
b1111 -
b1111 6
b1111 c
1J
0A
1Q
0O
1G
0I
1N
0D
1L
b1111 $
b1110 #
b1110 *
b1110 2
b1110 ;
b1110 >
b1110 b
b11110 '
b11110 (
#620000
1`
0_
1]
1?
b10000 !
b10000 ,
b10000 9
0X
1V
b10000 0
b10000 8
b10000 B
1@
b1 /
b1 3
b1 4
0Q
1O
b1110 -
b1110 6
b1110 c
0J
1A
0G
1I
1D
b10000 $
b1111 #
b1111 *
b1111 2
b1111 ;
b1111 >
b1111 b
b11111 '
b11111 (
#640000
b10 !
b10 ,
b10 9
0@
b10 0
b10 8
b10 B
b0 /
b0 3
b0 4
b10 .
b10 7
b10 <
1Q
0O
0?
0`
b10 -
b10 6
b10 c
0A
0X
0V
0_
0]
0I
0U
0\
0C
1K
0D
0L
0S
0Z
b10 $
b10 "
b10 )
b10 1
b10 :
b10 =
b10 a
b0 #
b0 *
b0 2
b0 ;
b0 >
b0 b
b100000 '
b100000 (
#660000
b11 !
b11 ,
b11 9
b11 0
b11 8
b11 B
b11 .
b11 7
b11 <
b11 -
b11 6
b11 c
1J
1G
1D
b11 $
b1 #
b1 *
b1 2
b1 ;
b1 >
b1 b
b100001 '
b100001 (
#680000
b100 !
b100 ,
b100 9
b100 0
b100 8
b100 B
b10 /
b10 3
b10 4
b10 .
b10 7
b10 <
1X
b0 -
b0 6
b0 c
0J
0Q
1@
0G
0N
1P
0D
1L
b100 $
b10 #
b10 *
b10 2
b10 ;
b10 >
b10 b
b100010 '
b100010 (
#700000
b101 !
b101 ,
b101 9
b101 0
b101 8
b101 B
b11 .
b11 7
b11 <
b1 -
b1 6
b1 c
1J
1G
1D
b101 $
b11 #
b11 *
b11 2
b11 ;
b11 >
b11 b
b100011 '
b100011 (
#720000
b110 !
b110 ,
b110 9
b110 0
b110 8
b110 B
0_
b0 /
b0 3
b0 4
b110 .
b110 7
b110 <
0?
b110 -
b110 6
b110 c
0J
1Q
0@
1X
0V
0G
1N
0P
1U
0D
0L
1S
b110 $
b100 #
b100 *
b100 2
b100 ;
b100 >
b100 b
b100100 '
b100100 (
#740000
b111 !
b111 ,
b111 9
b111 0
b111 8
b111 B
b111 .
b111 7
b111 <
b111 -
b111 6
b111 c
1J
1G
1D
b111 $
b101 #
b101 *
b101 2
b101 ;
b101 >
b101 b
b100101 '
b100101 (
#760000
b1000 !
b1000 ,
b1000 9
1_
b1000 0
b1000 8
b1000 B
1?
b10 /
b10 3
b10 4
b110 .
b110 7
b110 <
0X
1V
b100 -
b100 6
b100 c
0J
0Q
1@
0G
0N
1P
0D
1L
b1000 $
b110 #
b110 *
b110 2
b110 ;
b110 >
b110 b
b100110 '
b100110 (
#780000
b1001 !
b1001 ,
b1001 9
b1001 0
b1001 8
b1001 B
b111 .
b111 7
b111 <
b101 -
b101 6
b101 c
1J
1G
1D
b1001 $
b111 #
b111 *
b111 2
b111 ;
b111 >
b111 b
b100111 '
b100111 (
#800000
b1010 !
b1010 ,
b1010 9
b1010 0
b1010 8
b1010 B
b0 /
b0 3
b0 4
b1010 .
b1010 7
b1010 <
0?
0`
b1010 -
b1010 6
b1010 c
0J
1Q
0@
0X
0V
1_
0]
0G
1N
0P
0U
1\
0D
0L
0S
1Z
b1010 $
b1000 #
b1000 *
b1000 2
b1000 ;
b1000 >
b1000 b
b101000 '
b101000 (
#820000
b1011 !
b1011 ,
b1011 9
b1011 0
b1011 8
b1011 B
b1011 .
b1011 7
b1011 <
b1011 -
b1011 6
b1011 c
1J
1G
1D
b1011 $
b1001 #
b1001 *
b1001 2
b1001 ;
b1001 >
b1001 b
b101001 '
b101001 (
#840000
b1100 !
b1100 ,
b1100 9
b1100 0
b1100 8
b1100 B
b10 /
b10 3
b10 4
b1010 .
b1010 7
b1010 <
1X
b1000 -
b1000 6
b1000 c
0J
0Q
1@
0G
0N
1P
0D
1L
b1100 $
b1010 #
b1010 *
b1010 2
b1010 ;
b1010 >
b1010 b
b101010 '
b101010 (
#860000
b1101 !
b1101 ,
b1101 9
b1101 0
b1101 8
b1101 B
b1011 .
b1011 7
b1011 <
b1001 -
b1001 6
b1001 c
1J
1G
1D
b1101 $
b1011 #
b1011 *
b1011 2
b1011 ;
b1011 >
b1011 b
b101011 '
b101011 (
#880000
b1110 !
b1110 ,
b1110 9
0`
b1110 0
b1110 8
b1110 B
1_
0]
b0 /
b0 3
b0 4
b1110 .
b1110 7
b1110 <
0?
b1110 -
b1110 6
b1110 c
0J
1Q
0@
1X
0V
0G
1N
0P
1U
0D
0L
1S
b1110 $
b1100 #
b1100 *
b1100 2
b1100 ;
b1100 >
b1100 b
b101100 '
b101100 (
#900000
b1111 !
b1111 ,
b1111 9
b1111 0
b1111 8
b1111 B
b1111 .
b1111 7
b1111 <
b1111 -
b1111 6
b1111 c
1J
1G
1D
b1111 $
b1101 #
b1101 *
b1101 2
b1101 ;
b1101 >
b1101 b
b101101 '
b101101 (
#920000
1`
b10000 !
b10000 ,
b10000 9
0_
1]
b10000 0
b10000 8
b10000 B
1?
b10 /
b10 3
b10 4
b1110 .
b1110 7
b1110 <
0X
1V
b1100 -
b1100 6
b1100 c
0J
0Q
1@
0G
0N
1P
0D
1L
b10000 $
b1110 #
b1110 *
b1110 2
b1110 ;
b1110 >
b1110 b
b101110 '
b101110 (
#940000
b10001 !
b10001 ,
b10001 9
b10001 0
b10001 8
b10001 B
b1111 .
b1111 7
b1111 <
b1101 -
b1101 6
b1101 c
1J
1G
1D
b10001 $
b1111 #
b1111 *
b1111 2
b1111 ;
b1111 >
b1111 b
b101111 '
b101111 (
#960000
b11 !
b11 ,
b11 9
b11 0
b11 8
b11 B
b0 /
b0 3
b0 4
b11 .
b11 7
b11 <
0?
0`
b11 -
b11 6
b11 c
1Q
0@
0X
0V
0_
0]
1N
0P
0U
0\
1C
0D
0L
0S
0Z
b11 $
b11 "
b11 )
b11 1
b11 :
b11 =
b11 a
b0 #
b0 *
b0 2
b0 ;
b0 >
b0 b
b110000 '
b110000 (
#980000
b100 !
b100 ,
b100 9
1X
b100 0
b100 8
b100 B
1@
b1 /
b1 3
b1 4
0Q
1O
b10 -
b10 6
b10 c
0J
1A
0G
1I
1D
b100 $
b1 #
b1 *
b1 2
b1 ;
b1 >
b1 b
b110001 '
b110001 (
#1000000
b101 !
b101 ,
b101 9
b101 0
b101 8
b101 B
b10 /
b10 3
b10 4
1X
b1 -
b1 6
b1 c
1J
0A
0Q
0O
1@
0M
1G
0I
0N
1P
0D
1L
b101 $
b10 #
b10 *
b10 2
b10 ;
b10 >
b10 b
b110010 '
b110010 (
#1020000
b110 !
b110 ,
b110 9
b110 0
b110 8
b110 B
b11 /
b11 3
b11 4
1Q
b0 -
b0 6
b0 c
0J
1A
0G
1I
1D
b110 $
b11 #
b11 *
b11 2
b11 ;
b11 >
b11 b
b110011 '
b110011 (
#1040000
b111 !
b111 ,
b111 9
b111 0
b111 8
b111 B
0_
b0 /
b0 3
b0 4
b111 .
b111 7
b111 <
0?
b111 -
b111 6
b111 c
1J
0A
1Q
0O
0@
1X
0V
1G
0I
1N
0P
1U
0D
0L
1S
b111 $
b100 #
b100 *
b100 2
b100 ;
b100 >
b100 b
b110100 '
b110100 (
#1060000
1_
1?
b1000 !
b1000 ,
b1000 9
0X
1V
b1000 0
b1000 8
b1000 B
1@
b1 /
b1 3
b1 4
0Q
1O
b110 -
b110 6
b110 c
0J
1A
0G
1I
1D
b1000 $
b101 #
b101 *
b101 2
b101 ;
b101 >
b101 b
b110101 '
b110101 (
#1080000
b1001 !
b1001 ,
b1001 9
1_
b1001 0
b1001 8
b1001 B
1?
b10 /
b10 3
b10 4
0X
1V
b101 -
b101 6
b101 c
1J
0A
0Q
0O
1@
0M
1G
0I
0N
1P
0D
1L
b1001 $
b110 #
b110 *
b110 2
b110 ;
b110 >
b110 b
b110110 '
b110110 (
#1100000
b1010 !
b1010 ,
b1010 9
b1010 0
b1010 8
b1010 B
b11 /
b11 3
b11 4
1Q
b100 -
b100 6
b100 c
0J
1A
0G
1I
1D
b1010 $
b111 #
b111 *
b111 2
b111 ;
b111 >
b111 b
b110111 '
b110111 (
#1120000
b1011 !
b1011 ,
b1011 9
b1011 0
b1011 8
b1011 B
b0 /
b0 3
b0 4
b1011 .
b1011 7
b1011 <
0?
0`
b1011 -
b1011 6
b1011 c
1J
0A
1Q
0O
0@
0X
0V
1_
0]
1G
0I
1N
0P
0U
1\
0D
0L
0S
1Z
b1011 $
b1000 #
b1000 *
b1000 2
b1000 ;
b1000 >
b1000 b
b111000 '
b111000 (
#1140000
b1100 !
b1100 ,
b1100 9
1X
b1100 0
b1100 8
b1100 B
1@
b1 /
b1 3
b1 4
0Q
1O
b1010 -
b1010 6
b1010 c
0J
1A
0G
1I
1D
b1100 $
b1001 #
b1001 *
b1001 2
b1001 ;
b1001 >
b1001 b
b111001 '
b111001 (
#1160000
b1101 !
b1101 ,
b1101 9
b1101 0
b1101 8
b1101 B
b10 /
b10 3
b10 4
1X
b1001 -
b1001 6
b1001 c
1J
0A
0Q
0O
1@
0M
1G
0I
0N
1P
0D
1L
b1101 $
b1010 #
b1010 *
b1010 2
b1010 ;
b1010 >
b1010 b
b111010 '
b111010 (
#1180000
b1110 !
b1110 ,
b1110 9
b1110 0
b1110 8
b1110 B
b11 /
b11 3
b11 4
1Q
b1000 -
b1000 6
b1000 c
0J
1A
0G
1I
1D
b1110 $
b1011 #
b1011 *
b1011 2
b1011 ;
b1011 >
b1011 b
b111011 '
b111011 (
#1200000
b1111 !
b1111 ,
b1111 9
0`
b1111 0
b1111 8
b1111 B
1_
0]
b0 /
b0 3
b0 4
b1111 .
b1111 7
b1111 <
0?
b1111 -
b1111 6
b1111 c
1J
0A
1Q
0O
0@
1X
0V
1G
0I
1N
0P
1U
0D
0L
1S
b1111 $
b1100 #
b1100 *
b1100 2
b1100 ;
b1100 >
b1100 b
b111100 '
b111100 (
#1220000
1`
0_
1]
1?
b10000 !
b10000 ,
b10000 9
0X
1V
b10000 0
b10000 8
b10000 B
1@
b1 /
b1 3
b1 4
0Q
1O
b1110 -
b1110 6
b1110 c
0J
1A
0G
1I
1D
b10000 $
b1101 #
b1101 *
b1101 2
b1101 ;
b1101 >
b1101 b
b111101 '
b111101 (
#1240000
1`
b10001 !
b10001 ,
b10001 9
0_
1]
b10001 0
b10001 8
b10001 B
1?
b10 /
b10 3
b10 4
0X
1V
b1101 -
b1101 6
b1101 c
1J
0A
0Q
0O
1@
0M
1G
0I
0N
1P
0D
1L
b10001 $
b1110 #
b1110 *
b1110 2
b1110 ;
b1110 >
b1110 b
b111110 '
b111110 (
#1260000
b10010 !
b10010 ,
b10010 9
b10010 0
b10010 8
b10010 B
b11 /
b11 3
b11 4
1Q
b1100 -
b1100 6
b1100 c
0J
1A
0G
1I
1D
b10010 $
b1111 #
b1111 *
b1111 2
b1111 ;
b1111 >
b1111 b
b111111 '
b111111 (
